{
  "uptime": 95.8685423,
  "uptimeFormatted": "1m",
  "memory": {
    "rss": 139341824,
    "heapTotal": 78729216,
    "heapUsed": 75511288,
    "external": 3992627,
    "arrayBuffers": 109896
  },
  "nodeVersion": "v24.13.0",
  "pid": 65304,
  "botName": "Testbot#9379",
  "guildCount": 1,
  "timestamp": "2026-02-16T20:42:03.707Z",
  "status": "online",
  "autoSync": {
    "enabled": false,
    "interval": 300000,
    "intervalFormatted": "5 minutes",
    "channelId": null,
    "guildId": null
  },
  "backgroundSync": {
    "enabled": true,
    "interval": 300000,
    "intervalFormatted": "5 minutes"
  }
}